selenium_setup/__init__.py
selenium_setup/__main__.py
selenium_setup/_drivers.py
selenium_setup-1.1.0.dist-info/LICENSE
selenium_setup-1.1.0.dist-info/METADATA
selenium_setup-1.1.0.dist-info/WHEEL
selenium_setup-1.1.0.dist-info/entry_points.txt
selenium_setup-1.1.0.dist-info/RECORD
