Metadata-Version: 2.1
Name: selenium_setup
Version: 1.1.0
Summary: 
Home-page: https://github.com/m9810223/selenium_setup
Author:  
Requires-Python: >=3.7,<4
Classifier: Programming Language :: Python :: 3
Classifier: Programming Language :: Python :: 3.7
Classifier: Programming Language :: Python :: 3.8
Classifier: Programming Language :: Python :: 3.9
Classifier: Programming Language :: Python :: 3.10
Classifier: Programming Language :: Python :: 3.11
Requires-Dist: httpx
Requires-Dist: rich
Requires-Dist: typer[all]
Requires-Dist: xmltodict
Project-URL: Repository, https://github.com/m9810223/selenium_setup
